sandbox/set_path_for_notebooks.py
test_measure_process_lib-1.0.13.dist-info/licenses/LICENSE.md
tmpl/__init__.py
tmpl/tmp_code_generator.py
tmpl/tmpl_core.py
tmpl/tmpl_storage.py
tmpl/tmpl_support.py
tmpl/examples/BigExperiment.py
tmpl/examples/__init__.py
tmpl/examples/example_resistor_test.py
tmpl/examples/repeated_measurements.py
tmpl/examples/resistor_example.py
tmpl/examples/set_path_for_notebooks.py
test_measure_process_lib-1.0.13.dist-info/METADATA
test_measure_process_lib-1.0.13.dist-info/WHEEL
test_measure_process_lib-1.0.13.dist-info/top_level.txt
test_measure_process_lib-1.0.13.dist-info/RECORD
