Metadata-Version: 2.4
Name: test_measure_process_lib
Version: 1.0.13
Summary: Test, Measure and Process library. Framework for lab experiments.
Author-email: RedLegJed <rlj_pypi@nym.hush.com>
License: Apache License
Project-URL: Homepage, https://redlegjed.github.io/test_measure_process_lib/
Project-URL: Github, https://github.com/redlegjed/test_measure_process_lib
Keywords: lab,test,measurement,scientific,engineering
Classifier: License :: OSI Approved :: Apache Software License
Classifier: Programming Language :: Python
Classifier: Programming Language :: Python :: 3
Requires-Python: >=3.7
License-File: LICENSE.md
Dynamic: license-file
